AUTHORS.rst
CONTRIBUTING.rst
HISTORY.rst
LICENSE
MANIFEST.in
README.rst
setup.cfg
setup.py
botanick/Botanick.py
botanick/__init__.py
botanick/const.py
botanick/main.py
botanick.egg-info/PKG-INFO
botanick.egg-info/SOURCES.txt
botanick.egg-info/dependency_links.txt
botanick.egg-info/not-zip-safe
botanick.egg-info/top_level.txt
docs/Makefile
docs/conf.py
docs/index.rst
tests/__init__.py
tests/test_botanick.py