Metadata-Version: 1.1
Name: botanick
Version: 0.1.0
Summary: Botanick
Home-page: https://github.com/avidot/botanick
Author: Adrien VIDOT
Author-email: avidot@squad.pro
License: MIT license
Keywords: botanick
Platform: UNKNOWN
Classifier: Development Status :: 2 - Pre-Alpha
Classifier: Intended Audience :: Developers
Classifier: License :: OSI Approved :: MIT License
Classifier: Natural Language :: English
Classifier: Programming Language :: Python :: 3.5
